.hgignore
.hgtags
.noserc
.pydistutils.cfg
LICENSE.txt
MANIFEST.in
README.rst
requirements.txt
setup.cfg
setup.py
tox.ini
src/blueberrypy/__init__.py
src/blueberrypy/command.py
src/blueberrypy/config.py
src/blueberrypy/console.py
src/blueberrypy/email.py
src/blueberrypy/exc.py
src/blueberrypy/plugins.py
src/blueberrypy/project.py
src/blueberrypy/session.py
src/blueberrypy/template_engine.py
src/blueberrypy/testing.py
src/blueberrypy/tools.py
src/blueberrypy/util.py
src/blueberrypy.egg-info/PKG-INFO
src/blueberrypy.egg-info/SOURCES.txt
src/blueberrypy.egg-info/dependency_links.txt
src/blueberrypy.egg-info/entry_points.txt
src/blueberrypy.egg-info/not-zip-safe
src/blueberrypy.egg-info/requires.txt
src/blueberrypy.egg-info/top_level.txt
src/blueberrypy/project_template/setup.py_tmpl
src/blueberrypy/project_template/.cache/.hidden
src/blueberrypy/project_template/config/dev/app.yml_tmpl
src/blueberrypy/project_template/config/dev/bundles.yml_tmpl
src/blueberrypy/project_template/config/dev/logging.yml_tmpl
src/blueberrypy/project_template/config/prod/app.yml_tmpl
src/blueberrypy/project_template/config/prod/bundles.yml_tmpl
src/blueberrypy/project_template/config/prod/logging.yml_tmpl
src/blueberrypy/project_template/log/.hidden
src/blueberrypy/project_template/src/+package+/__init__.py_tmpl
src/blueberrypy/project_template/src/+package+/api.py_tmpl
src/blueberrypy/project_template/src/+package+/controller.py_tmpl
src/blueberrypy/project_template/src/+package+/model.py_tmpl
src/blueberrypy/project_template/src/+package+/rest_controller.py_tmpl
src/blueberrypy/project_template/src/+package+/templates/404.html
src/blueberrypy/project_template/src/+package+/templates/base.html_tmpl
src/blueberrypy/project_template/src/+package+/templates/index.html
src/blueberrypy/project_template/src/tests/__init__.py_tmpl
src/blueberrypy/project_template/src/tests/helper.py_tmpl
src/blueberrypy/project_template/src/tests/test_api.py_tmpl
src/blueberrypy/project_template/src/tests/test_controller.py_tmpl
src/blueberrypy/project_template/src/tests/test_model.py_tmpl
src/blueberrypy/project_template/src/tests/test_rest_controller.py_tmpl
src/blueberrypy/project_template/static/favicon.ico
src/blueberrypy/project_template/static/css/screen.css
