Metadata-Version: 1.0
Name: blueberrypy
Version: 0.5.1
Summary: CherryPy plugins and tools for integration with various libraries, including logging, Redis, SQLAlchemy and Jinja2 and webassets.
Home-page: http://bitbucket.org/wyuenho/blueberrypy
Author: Jimmy Yuen Ho Wong
Author-email: wyuenho@gmail.com
License: BSD
Platform: UNKNOWN
Classifier: Development Status :: 4 - Beta
Classifier: Environment :: Plugins
Classifier: Environment :: Web Environment
Classifier: Framework :: CherryPy
Classifier: Intended Audience :: Developers
Classifier: License :: OSI Approved :: BSD License
Classifier: Natural Language :: English
Classifier: Operating System :: OS Independent
Classifier: Programming Language :: Python :: 2.6
Classifier: Programming Language :: Python :: 2.7
Classifier: Topic :: Database
Classifier: Topic :: Internet :: WWW/HTTP :: Session
Classifier: Topic :: Software Development :: Libraries
Classifier: Topic :: Utilities
